outliers/out.py
outlier_removal3054-3.1.2.dist-info/LICENSE.txt
outlier_removal3054-3.1.2.dist-info/METADATA
outlier_removal3054-3.1.2.dist-info/WHEEL
outlier_removal3054-3.1.2.dist-info/entry_points.txt
outlier_removal3054-3.1.2.dist-info/top_level.txt
outlier_removal3054-3.1.2.dist-info/RECORD
