Metadata-Version: 2.1
Name: outlier-removal3054
Version: 3.1.2
Summary: A Python package for removing outliers in dataset using the Interquartile Range technique.
Home-page: UNKNOWN
Author: Mehak garg
Author-email: mehakgarg426@gmail.com
License: MIT
Platform: UNKNOWN
Classifier: License :: OSI Approved :: MIT License
Classifier: Programming Language :: Python :: 3
Classifier: Programming Language :: Python :: 3.7
Requires-Dist: pandas
Requires-Dist: numpy
